REG/regfile.v
//----------------------------------------------------------------------------
// Module: regfile.v
// Register file with two read ports and one write port
//----------------------------------------------------------------------------
module regfile #(
  parameter DATA_WIDTH    = 16,
  parameter REGADDR_WIDTH = 4,
  parameter NUM_REGS      = (1<<REGADDR_WIDTH)
) (
  input                        clk,
  input                        reset,
  input      [REGADDR_WIDTH-1:0] read_reg1,
  input      [REGADDR_WIDTH-1:0] read_reg2,
  output     [DATA_WIDTH-1:0]    read_data1,
  output     [DATA_WIDTH-1:0]    read_data2,
  input      [REGADDR_WIDTH-1:0] write_reg,
  input      [DATA_WIDTH-1:0]    write_data,
  input                        reg_write
);

  reg [DATA_WIDTH-1:0] regs [0:NUM_REGS-1];

  // write-first (forward write_data on a matched read_reg)
  assign read_data1 = (reg_write && (write_reg == read_reg1))
                      ? write_data
                      : regs[read_reg1];
  assign read_data2 = (reg_write && (write_reg == read_reg2))
                      ? write_data
                      : regs[read_reg2];

  always @(posedge clk or posedge reset) begin
    if (reset) begin
      integer i;
      for (i=0; i<NUM_REGS; i=i+1)
        regs[i] <= 0;
    end else if (reg_write) begin
      regs[write_reg] <= write_data;
    end
  end

endmodule

REG/regfile_tb.v
`timescale 1ns / 1ps

module tb_regfile;
  // Parameters must match your regfile
  localparam DATA_WIDTH    = 16;
  localparam REGADDR_WIDTH = 3;
  localparam NUM_REGS      = 1 << REGADDR_WIDTH;

  // DUT I/O
  reg                          clk;
  reg                          reset;
  reg                          reg_write;
  reg  [REGADDR_WIDTH-1:0]     read_reg1;
  reg  [REGADDR_WIDTH-1:0]     read_reg2;
  reg  [REGADDR_WIDTH-1:0]     write_reg;
  reg  [DATA_WIDTH-1:0]        write_data;
  wire [DATA_WIDTH-1:0]        read_data1;
  wire [DATA_WIDTH-1:0]        read_data2;

  // Instantiate the register file
  regfile #(
    .DATA_WIDTH(DATA_WIDTH),
    .REGADDR_WIDTH(REGADDR_WIDTH)
  ) DUT (
    .clk(clk),
    .reset(reset),
    .reg_write(reg_write),
    .read_reg1(read_reg1),
    .read_reg2(read_reg2),
    .write_reg(write_reg),
    .write_data(write_data),
    .read_data1(read_data1),
    .read_data2(read_data2)
  );

  // Clock generation
  initial begin
    clk = 0;
    forever #5 clk = ~clk;  // 100 MHz clock
  end

  // Test sequence
  integer i;
  reg [DATA_WIDTH-1:0] golden [0:NUM_REGS-1];

  initial begin
    $dumpfile("regfile_tb.vcd");
    $dumpvars(0, tb_regfile);

    // 1) Reset and check all regs = 0
    reset = 1; reg_write = 0;
    read_reg1 = 0; read_reg2 = 1;
    #10;
    for (i = 0; i < NUM_REGS; i = i + 1) begin
      read_reg1 = i; #1;
      if (read_data1 !== 0) $display("ERROR: R%0d != 0 after reset (got %h)", i, read_data1);
    end

    // deassert reset
    reset = 0; #10;

    // 2) Write distinct values into each register
    for (i = 0; i < NUM_REGS; i = i + 1) begin
      golden[i]   = i * 16'h1111;  // some pattern
      reg_write   = 1;
      write_reg   = i;
      write_data  = golden[i];
      #10;                         // wait one clock
    end

    // turn off writes
    reg_write = 0; #10;

    // 3) Read back all registers (two at a time) and compare
    for (i = 0; i < NUM_REGS; i = i + 2) begin
      read_reg1 = i;
      read_reg2 = i+1;
      #1;  // combinational read
      if (read_data1 !== golden[i]) $display("ERROR: R%0d = %h, expected %h", i, read_data1, golden[i]);
      if (read_data2 !== golden[i+1]) $display("ERROR: R%0d = %h, expected %h", i+1, read_data2, golden[i+1]);
      else $display("PASS: R%0d=%h, R%0d=%h", i, read_data1, i+1, read_data2);
      #9;  // move to next clock boundary
    end

    $display("regfile test complete");
    $finish;
  end
endmodule

REG/regfile_tb.vcd
$date
	Fri May 16 16:43:30 2025
$end
$version
	Icarus Verilog
$end
$timescale
	1ps
$end
$scope module tb_regfile $end
$var wire 16 ! read_data2 [15:0] $end
$var wire 16 " read_data1 [15:0] $end
$var parameter 32 # DATA_WIDTH $end
$var parameter 35 $ NUM_REGS $end
$var parameter 32 % REGADDR_WIDTH $end
$var reg 1 & clk $end
$var reg 3 ' read_reg1 [2:0] $end
$var reg 3 ( read_reg2 [2:0] $end
$var reg 1 ) reg_write $end
$var reg 1 * reset $end
$var reg 16 + write_data [15:0] $end
$var reg 3 , write_reg [2:0] $end
$var integer 32 - i [31:0] $end
$scope module DUT $end
$var wire 1 & clk $end
$var wire 16 . read_data1 [15:0] $end
$var wire 16 / read_data2 [15:0] $end
$var wire 3 0 read_reg1 [2:0] $end
$var wire 3 1 read_reg2 [2:0] $end
$var wire 1 ) reg_write $end
$var wire 1 * reset $end
$var wire 16 2 write_data [15:0] $end
$var wire 3 3 write_reg [2:0] $end
$var parameter 32 4 DATA_WIDTH $end
$var parameter 35 5 NUM_REGS $end
$var parameter 32 6 REGADDR_WIDTH $end
$var integer 32 7 i [31:0] $end
$upscope $end
$upscope $end
$enddefinitions $end
$comment Show the parameter values. $end
$dumpall
b11 6
b1000 5
b10000 4
b11 %
b1000 $
b10000 #
$end
#0
$dumpvars
b1000 7
bx 3
bx 2
b1 1
b0 0
b0 /
b0 .
bx -
bx ,
bx +
1*
0)
b1 (
b0 '
0&
b0 "
b0 !
$end
#5000
b1000 7
1&
#10000
0&
b0 -
#11000
b1 '
b1 0
b1 -
#12000
b10 '
b10 0
b10 -
#13000
b11 '
b11 0
b11 -
#14000
b100 '
b100 0
b100 -
#15000
b1000 7
b101 '
b101 0
b101 -
1&
#16000
b110 '
b110 0
b110 -
#17000
b111 '
b111 0
b111 -
#18000
0*
b1000 -
#20000
0&
#25000
1&
#28000
b0 +
b0 2
b0 ,
b0 3
1)
b0 -
#30000
0&
#35000
1&
#38000
b1000100010001 +
b1000100010001 2
b1 ,
b1 3
b1 -
#40000
0&
#45000
b1000100010001 !
b1000100010001 /
1&
#48000
b10001000100010 +
b10001000100010 2
b10 ,
b10 3
b10 -
#50000
0&
#55000
1&
#58000
b11001100110011 +
b11001100110011 2
b11 ,
b11 3
b11 -
#60000
0&
#65000
1&
#68000
b100010001000100 +
b100010001000100 2
b100 ,
b100 3
b100 -
#70000
0&
#75000
1&
#78000
b101010101010101 +
b101010101010101 2
b101 ,
b101 3
b101 -
#80000
0&
#85000
1&
#88000
b110011001100110 +
b110011001100110 2
b110 ,
b110 3
b110 -
#90000
0&
#95000
1&
#98000
b111011101110111 +
b111011101110111 2
b111 ,
b111 3
b111 -
#100000
0&
#105000
b111011101110111 "
b111011101110111 .
1&
#108000
0)
b1000 -
#110000
0&
#115000
1&
#118000
b0 "
b0 .
b0 '
b0 0
b0 -
#120000
0&
#125000
1&
#128000
b11001100110011 !
b11001100110011 /
b11 (
b11 1
b10001000100010 "
b10001000100010 .
b10 '
b10 0
b10 -
#130000
0&
#135000
1&
#138000
b101010101010101 !
b101010101010101 /
b101 (
b101 1
b100010001000100 "
b100010001000100 .
b100 '
b100 0
b100 -
#140000
0&
#145000
1&
#148000
b111011101110111 !
b111011101110111 /
b111 (
b111 1
b110011001100110 "
b110011001100110 .
b110 '
b110 0
b110 -
#150000
0&
#155000
1&
#158000
b1000 -
