ALU/ALU.v
`timescale 1ns / 1ps

//----------------------------------------------------------------------------
// Module: alu.v
// A simple 2‑operand ALU with add, xor, and pass‑through (for mov/ldpc).
//----------------------------------------------------------------------------
module alu #(
    parameter WIDTH = 16
) (
    input  [WIDTH-1:0] a,      // operand A (e.g. Rs)
    input  [WIDTH-1:0] b,      // operand B (e.g. Rt or imm)
    input  [1:0]       alu_op, // 00 = add, 01 = xor, 10 = pass B, others = reserved/zero
    output reg [WIDTH-1:0] result,
    output                zero  // high if result == 0
);

    // combinational operation
    always @(*) begin
        case (alu_op)
            2'b00: result = a + b;       // ADD
            2'b01: result = a ^ b;       // XOR
            2'b10: result = b;           // PASS‑B (mov/ldpc/load)
            2'b11: result = a - b;       // SUBTRACTION
            default: result = {WIDTH{1'b0}};
        endcase
    end

    // zero flag
    assign zero = (result == {WIDTH{1'b0}});

endmodule

ALU/alu_tb.v
`timescale 1ns / 1ps

module tb_alu;
  // parameters must match your alu.v
  parameter WIDTH = 16;
  
  // DUT I/O
  reg  [WIDTH-1:0] a;
  reg  [WIDTH-1:0] b;
  reg  [1:0]       alu_op;
  wire [WIDTH-1:0] result;
  wire             zero;
  
  // loop counter
  integer i;
  
  // Instantiate the ALU
  alu #(.WIDTH(WIDTH)) DUT (
    .a(a),
    .b(b),
    .alu_op(alu_op),
    .result(result),
    .zero(zero)
  );
  
  // Test vectors
  reg [WIDTH-1:0] a_vec [0:7];
  reg [WIDTH-1:0] b_vec [0:7];
  reg [1:0]       op_vec[0:7];
  reg [WIDTH-1:0] expected [0:7];
  reg             exp_zero [0:7];
  
  initial begin
    // Dump for GTKWave
    $dumpfile("alu_tb.vcd");
    $dumpvars(0, tb_alu);
    
    // Define 8 test cases
    // format: {a, b, alu_op, expected_result, expected_zero}
    a_vec[0] = 16'h0001; b_vec[0] = 16'h0001; op_vec[0] = 2'b00; expected[0] = 16'h0002; exp_zero[0] = 1'b0; // 1+1=2
    a_vec[1] = 16'h0005; b_vec[1] = 16'h0003; op_vec[1] = 2'b01; expected[1] = 16'h0006; exp_zero[1] = 1'b0; // 5^3=6
    a_vec[2] = 16'h00FF; b_vec[2] = 16'h0001; op_vec[2] = 2'b10; expected[2] = 16'h0001; exp_zero[2] = 1'b0; // pass B
    a_vec[3] = 16'h000A; b_vec[3] = 16'h0003; op_vec[3] = 2'b11; expected[3] = 16'h0007; exp_zero[3] = 1'b0; // 10-3=7
    a_vec[4] = 16'h0008; b_vec[4] = 16'h0008; op_vec[4] = 2'b11; expected[4] = 16'h0000; exp_zero[4] = 1'b1; // 8-8=0 -> zero
    a_vec[5] = 16'h1234; b_vec[5] = 16'h4321; op_vec[5] = 2'b00; expected[5] = 16'h5555; exp_zero[5] = 1'b0; // add
    a_vec[6] = 16'hFFFF; b_vec[6] = 16'h0000; op_vec[6] = 2'b01; expected[6] = 16'hFFFF; exp_zero[6] = 1'b0; // xor
    a_vec[7] = 16'hABCD; b_vec[7] = 16'h0010; op_vec[7] = 2'b10; expected[7] = 16'h0010; exp_zero[7] = 1'b0; // pass B
    
    // Apply test vectors
    for (i = 0; i < 8; i = i + 1) begin
      // drive inputs
      a      = a_vec[i];
      b      = b_vec[i];
      alu_op = op_vec[i];
      
      // wait for combinational result to settle
      #5;
      
      // check
      if (result !== expected[i] || zero !== exp_zero[i]) begin
        $display("FAILED case %0d: a=%h b=%h op=%b => got result=%h zero=%b, expected %h/%b",
                 i, a, b, alu_op, result, zero, expected[i], exp_zero[i]);
      end else begin
        $display("PASSED case %0d", i);
      end
    end
    
    $display("All tests done.");
    $finish;
  end
endmodule

ALU/alu_tb.vcd
$date
	Thu May 15 14:24:07 2025
$end
$version
	Icarus Verilog
$end
$timescale
	1ps
$end
$scope module tb_alu $end
$var wire 1 ! zero $end
$var wire 16 " result [15:0] $end
$var parameter 32 # WIDTH $end
$var reg 16 $ a [15:0] $end
$var reg 2 % alu_op [1:0] $end
$var reg 16 & b [15:0] $end
$var integer 32 ' i [31:0] $end
$scope module DUT $end
$var wire 16 ( a [15:0] $end
$var wire 2 ) alu_op [1:0] $end
$var wire 16 * b [15:0] $end
$var wire 1 ! zero $end
$var parameter 32 + WIDTH $end
$var reg 16 , result [15:0] $end
$upscope $end
$upscope $end
$enddefinitions $end
$comment Show the parameter values. $end
$dumpall
b10000 +
b10000 #
$end
#0
$dumpvars
b10 ,
b1 *
b0 )
b1 (
b0 '
b1 &
b0 %
b1 $
b10 "
0!
$end
#5000
b110 "
b110 ,
b1 %
b1 )
b11 &
b11 *
b101 $
b101 (
b1 '
#10000
b1 "
b1 ,
b10 %
b10 )
b1 &
b1 *
b11111111 $
b11111111 (
b10 '
#15000
b111 "
b111 ,
b11 %
b11 )
b11 &
b11 *
b1010 $
b1010 (
b11 '
#20000
1!
b0 "
b0 ,
b1000 &
b1000 *
b1000 $
b1000 (
b100 '
#25000
0!
b101010101010101 "
b101010101010101 ,
b0 %
b0 )
b100001100100001 &
b100001100100001 *
b1001000110100 $
b1001000110100 (
b101 '
#30000
b1111111111111111 "
b1111111111111111 ,
b1 %
b1 )
b0 &
b0 *
b1111111111111111 $
b1111111111111111 (
b110 '
#35000
b10000 "
b10000 ,
b10 %
b10 )
b10000 &
b10000 *
b1010101111001101 $
b1010101111001101 (
b111 '
#40000
b1000 '
